LICENSE.md
MANIFEST.in
README.rst
pyproject.toml
requirements.allauth.txt
requirements.auth.txt
requirements.core.txt
requirements.dev.txt
requirements.mongo.txt
requirements.txt
setup.py
core_main_app/__init__.py
core_main_app/admin.py
core_main_app/apps.py
core_main_app/menus.py
core_main_app/models.py
core_main_app/settings.py
core_main_app/urls.py
core_main_app.egg-info/PKG-INFO
core_main_app.egg-info/SOURCES.txt
core_main_app.egg-info/dependency_links.txt
core_main_app.egg-info/requires.txt
core_main_app.egg-info/top_level.txt
core_main_app/access_control/__init__.py
core_main_app/access_control/api.py
core_main_app/access_control/decorators.py
core_main_app/access_control/exceptions.py
core_main_app/access_control/utils.py
core_main_app/blob_modules/__init__.py
core_main_app/blob_modules/file_metadata.py
core_main_app/commons/__init__.py
core_main_app/commons/constants.py
core_main_app/commons/enums.py
core_main_app/commons/exceptions.py
core_main_app/commons/regex.py
core_main_app/commons/serializers.py
core_main_app/commons/validators.py
core_main_app/components/__init__.py
core_main_app/components/abstract_data/__init__.py
core_main_app/components/abstract_data/models.py
core_main_app/components/abstract_processing_module/__init__.py
core_main_app/components/abstract_processing_module/admin_site.py
core_main_app/components/abstract_processing_module/models.py
core_main_app/components/blob/__init__.py
core_main_app/components/blob/access_control.py
core_main_app/components/blob/admin_site.py
core_main_app/components/blob/api.py
core_main_app/components/blob/models.py
core_main_app/components/blob/utils.py
core_main_app/components/blob_processing_module/__init__.py
core_main_app/components/blob_processing_module/admin_site.py
core_main_app/components/blob_processing_module/api.py
core_main_app/components/blob_processing_module/models.py
core_main_app/components/blob_processing_module/signals.py
core_main_app/components/blob_processing_module/tasks.py
core_main_app/components/data/__init__.py
core_main_app/components/data/access_control.py
core_main_app/components/data/admin_site.py
core_main_app/components/data/api.py
