Metadata-Version: 2.1
Name: core-main-app
Version: 2.19.0
Summary: Main functionalities for the curator core project
Home-page: https://github.com/usnistgov/core_main_app
Author: NIST IT Lab
Author-email: itl_inquiries@nist.gov
Requires-Python: >=3.9
Provides-Extra: develop
Provides-Extra: mongodb
Provides-Extra: auth
Provides-Extra: allauth
License-File: LICENSE.md
